README.rst
setup.cfg
setup.py
src/roswire/__init__.py
src/roswire/description.py
src/roswire/exceptions.py
src/roswire/name.py
src/roswire/roswire.py
src/roswire/system.py
src/roswire/util.py
src/roswire/version.py
src/roswire.egg-info/PKG-INFO
src/roswire.egg-info/SOURCES.txt
src/roswire.egg-info/dependency_links.txt
src/roswire.egg-info/requires.txt
src/roswire.egg-info/top_level.txt
src/roswire/bag/__init__.py
src/roswire/bag/core.py
src/roswire/bag/daikon.py
src/roswire/bag/reader.py
src/roswire/bag/writer.py
src/roswire/definitions/__init__.py
src/roswire/definitions/action.py
src/roswire/definitions/base.py
src/roswire/definitions/decode.py
src/roswire/definitions/encode.py
src/roswire/definitions/format.py
src/roswire/definitions/msg.py
src/roswire/definitions/package.py
src/roswire/definitions/srv.py
src/roswire/definitions/type_db.py
src/roswire/proxy/__init__.py
src/roswire/proxy/bag.py
src/roswire/proxy/catkin.py
src/roswire/proxy/container.py
src/roswire/proxy/node.py
src/roswire/proxy/parameters.py
src/roswire/proxy/roscore.py
src/roswire/proxy/service.py
src/roswire/proxy/state.py
src/roswire/proxy/tcpros.py
src/roswire/proxy/roslaunch/__init__.py
src/roswire/proxy/roslaunch/context.py
src/roswire/proxy/roslaunch/controller.py
src/roswire/proxy/roslaunch/reader.py
src/roswire/proxy/roslaunch/roslaunch.py
src/roswire/proxy/roslaunch/rosparam.py
src/roswire/proxy/roslaunch/substitution.py
src/roswire/proxy/roslaunch/config/__init__.py
src/roswire/proxy/roslaunch/config/env.py
src/roswire/proxy/roslaunch/config/launch.py
src/roswire/proxy/roslaunch/config/node.py
src/roswire/proxy/roslaunch/config/parameter.py
test/test_bag.py
test/test_basic.py
test/test_format.py
test/test_hello_world.py
test/test_message.py
test/test_name.py
test/test_package.py
test/test_primitives.py
test/test_roscore.py
test/test_roslaunch.py
test/test_tcpros.py
test/test_type_database.py