Metadata-Version: 2.1
Name: roswire
Version: 1.4.0
Summary: An API for testing and mutating Dockerised ROS systems.
Home-page: https://github.com/ChrisTimperley/roswire
Author: Christopher Timperley
Author-email: christimperley@googlemail.com
License: Apache License, Version 2.0
Keywords: ros,docker,testing,analysis,mutation,repair
Platform: UNKNOWN
Classifier: Natural Language :: English
Classifier: Intended Audience :: Developers
Classifier: Programming Language :: Python
Classifier: Programming Language :: Python :: 3
Classifier: Programming Language :: Python :: 3.6
Classifier: Programming Language :: Python :: 3.7
Requires-Python: >=3.6
Provides-Extra: test
Provides-Extra: build_sphinx
